django_rest_params/__init__.py
django_rest_params/decorators.py
django_rest_params-1.0.2.dist-info/DESCRIPTION.rst
django_rest_params-1.0.2.dist-info/METADATA
django_rest_params-1.0.2.dist-info/metadata.json
django_rest_params-1.0.2.dist-info/RECORD
django_rest_params-1.0.2.dist-info/top_level.txt
django_rest_params-1.0.2.dist-info/WHEEL
