Metadata-Version: 2.0
Name: django-rest-params
Version: 1.0.2
Summary: Function decorator for Django REST Framework for specifying and constraining API parameters.
Home-page: https://github.com/cammsaul/django-rest-params
Author: Cam Saül
Author-email: cammsaul@gmail.com
License: BSD
Keywords: rest,django,api,params,parameters,djangorestframework,decorator
Platform: UNKNOWN
Classifier: Development Status :: 5 - Production/Stable
Classifier: Environment :: Web Environment
Classifier: Framework :: Django
Classifier: Intended Audience :: Developers
Classifier: Intended Audience :: System Administrators
Classifier: Operating System :: OS Independent
Classifier: Topic :: Software Development
Classifier: Topic :: Internet :: WWW/HTTP
Classifier: License :: OSI Approved :: BSD License
Classifier: Programming Language :: Python :: 2.7
Requires-Dist: django
Requires-Dist: djangorestframework
